hopper_api/__init__.py
hopper_api/app.py
hopper_api/crypto.py
hopper_api/hopper_api.py
hopper_api/notification.py
hopper_api-0.3.3.dist-info/METADATA
hopper_api-0.3.3.dist-info/WHEEL
hopper_api-0.3.3.dist-info/top_level.txt
hopper_api-0.3.3.dist-info/RECORD
