Metadata-Version: 2.1
Name: hopper-api
Version: 0.3.3
Summary: Hopper's app API
Home-page: https://github.com/hopper-team/hopper-api
Author: The hopper team
Author-email: info@hoppercloud.net
License: UNKNOWN
Platform: UNKNOWN
Classifier: Programming Language :: Python :: 3
Classifier: License :: OSI Approved :: MIT License
Classifier: Operating System :: OS Independent
Requires-Python: >=3.6
Requires-Dist: pyjwt
Requires-Dist: cryptography
Requires-Dist: requests
